wilfred/__init__.py
wilfred/container_variables.py
wilfred/core.py
wilfred/database.py
wilfred/decorators.py
wilfred/docker_conn.py
wilfred/errors.py
wilfred/keyboard.py
wilfred/message_handler.py
wilfred/migrate.py
wilfred/version.py
wilfred/wilfred.py
wilfred/api/__init__.py
wilfred/api/config_parser.py
wilfred/api/images.py
wilfred/api/server_config.py
wilfred/api/servers.py
wilfred/api/parser/__init__.py
wilfred/api/parser/json.py
wilfred/api/parser/properties.py
wilfred/api/parser/yaml.py
wilfred-0.10.1.dist-info/LICENSE
wilfred-0.10.1.dist-info/METADATA
wilfred-0.10.1.dist-info/WHEEL
wilfred-0.10.1.dist-info/entry_points.txt
wilfred-0.10.1.dist-info/top_level.txt
wilfred-0.10.1.dist-info/RECORD
