Metadata-Version: 2.1
Name: wilfred
Version: 0.10.1
Summary: A CLI for managing game servers using Docker.
Home-page: https://wilfredproject.org
Author: Vilhelm Prytz
Author-email: vlhelm@prytznet.se
License: MIT
Project-URL: Documentation, https://docs.wilfredproject.org
Project-URL: Code, https://github.com/wilfred-dev/wilfred
Project-URL: Issue tracker, https://github.com/wilfred-dev/wilfred/issues
Platform: UNKNOWN
Classifier: Programming Language :: Python
Classifier: Programming Language :: Python :: 3.7
Classifier: Programming Language :: Python :: 3.8
Classifier: Programming Language :: Python :: 3.9
Classifier: Programming Language :: Python :: 3.10
Classifier: Programming Language :: Python :: 3 :: Only
Classifier: Environment :: Console
Classifier: License :: OSI Approved :: MIT License
Classifier: Operating System :: MacOS :: MacOS X
Classifier: Operating System :: POSIX :: Linux
Classifier: Operating System :: Unix
Classifier: Operating System :: Microsoft :: Windows
Classifier: Natural Language :: English
Requires-Python: >=3.7
License-File: LICENSE
Requires-Dist: docker
Requires-Dist: click
Requires-Dist: colorama
Requires-Dist: appdirs
Requires-Dist: requests
Requires-Dist: tabulate
Requires-Dist: halo
Requires-Dist: sqlalchemy
Requires-Dist: pyyaml
Requires-Dist: pypiwin32 ; platform_system == "Windows"
